README
SConstruct
setup.py
external/antlr2.jar
external/antlr3.jar
external/stringtemplate-3.0.jar
ez_setup/README.txt
ez_setup/__init__.py
gcal2gcal.egg-info/PKG-INFO
gcal2gcal.egg-info/SOURCES.txt
gcal2gcal.egg-info/dependency_links.txt
gcal2gcal.egg-info/entry_points.txt
gcal2gcal.egg-info/requires.txt
gcal2gcal.egg-info/top_level.txt
src/LUADict.g
src/LUADict.tokens
src/LUADictLexer.py
src/LUADictParser.py
src/LUADict__.g
src/antlr3.py
src/gcal2gcal.py
src/plistservices.py
src/wxgc2gc.py