Metadata-Version: 1.0
Name: gcal2gcal
Version: 1.0.1
Summary: Package to upload GroupCalendar events to Google Calendar
Home-page: http://code.google.com/p/gcal2gcal/
Author: Grentius
Author-email: grentius@mailmight.com
License: BSD
Platform: UNKNOWN
